cotb/__init__.py
cotb-0.1.0.dist-info/METADATA
cotb-0.1.0.dist-info/WHEEL
cotb-0.1.0.dist-info/entry_points.txt
cotb-0.1.0.dist-info/top_level.txt
cotb-0.1.0.dist-info/RECORD
