Metadata-Version: 2.1
Name: cotb
Version: 0.1.0
Summary: cotb is a short name for click-outside-the-box, a program register and replay clicks for online card gaming
Author: Anthon van der Neut
Author-email: a.van.der.neut@ruamel.eu
License: Copyright Ruamel bvba 2007-2024
Project-URL: Home, https://sourceforge.net/p/click-outside-the-box/
Project-URL: Source, https://sourceforge.net/p/click-outside-the-box/code/ci/default/tree/
Project-URL: Tracker, https://sourceforge.net/p/click-outside-the-box/tickets/
Keywords: pypi gaming
Classifier: Development Status :: 4 - Beta
Classifier: Intended Audience :: Developers
Classifier: License :: Other/Proprietary License
Classifier: Operating System :: OS Independent
Classifier: Programming Language :: Python
Requires-Python: >=3.8
Requires-Dist: click-outside-the-box
